Workbook

Sheet How to use
B2: CallFlow AI — Lead Tracker
B3: Track every HVAC company you contact, from first look to paying customer.
B5: Colour legend
B6: Pale yellow cells | C6: You type here (company info, test results, stage, dates, notes).
B7: Grey cells | C7: Formulas. They fill in automatically; don't type over them.
B8: Green row | C8: Row 5 on the Leads tab is a fictional EXAMPLE showing the format. Delete it or overwrite it with a real company.
B10: Weekly routine
B11: 1. Find (Monday) | C11: Search Google Maps for 'HVAC [city] UT' (Salt Lake City, Sandy, West Jordan, Provo, Orem, Layton, Ogden…). Add 25 companies: name, phone, website, city, Google rating and review count.
B12: 2. Test (evenings) | C12: Call each new company between 6–9 PM. Record the date/time and what happened in the 'After-hours result' column. Voicemail / No answer → Priority becomes High automatically.
B13: 3. Contact (Tue–Thu) | C13: Email or call the High-priority companies first using sales/02-email-templates.md and sales/03-phone-and-walk-in-scripts.md. Update Stage and Last contact.
B14: 4. Follow up (Friday) | C14: Sort or filter by 'Next follow-up'. Rows turn red when a follow-up is overdue.
B15: 5. Review (Friday) | C15: Check the Pipeline tab: how many are in each stage, and your monthly recurring revenue (MRR).
B17: Stage definitions (Stage column)
B18: New | C18: Added to the list, not contacted yet
B19: Contacted | C19: First email, call or visit done
B20: Replied | C20: They responded (any answer except a clear no)
B21: Meeting booked | C21: Demo meeting on the calendar
B22: Demo done | C22: You showed them CallFlow
B23: Pilot | C23: Free 30-day pilot running
B24: Paying | C24: Paying customer (choose a Plan)
B25: Not now | C25: Interested later; set a Next follow-up date
B26: Not interested | C26: Clear no. Don't contact again
B28: Rules
B29: Email (CAN-SPAM) | C29: Real name, a postal address, and an opt-out line in every email. Honor opt-outs immediately; mark them 'Not interested'.
B30: No texting prospects | C30: Don't text or auto-dial companies that haven't agreed to it (TCPA). Email, hand-dialed calls and visits are fine.
B31: Privacy | C31: Only record business contact details you found publicly or they gave you.

Sheet Leads
A1: Leads
A2: Type in pale-yellow columns. Grey columns calculate automatically. Row 5 is a fictional example.
A4: Company | B4: Owner / contact | C4: Phone | D4: Email | E4: Website | F4: City | G4: Techs (est.) | H4: Google rating | I4: Review count | J4: Source | K4: After-hours test (date & time) | L4: After-hours result | M4: Priority | N4: Stage | O4: Last contact | P4: Next step | Q4: Next follow-up | R4: Days until follow-up | S4: Plan | T4: Monthly $ | U4: Notes
A5: EXAMPLE — Wasatch Comfort Heating & Air (fictional) | B5: Mike Jensen | C5: (801) 555-0100 | D5: mike@example.com | E5: example.com | F5: Sandy | G5: 6 | H5: 4.6 | I5: 87 | J5: Google Maps | K5: 46289.819 | L5: Voicemail | M5: =IF(L5="","",IF(OR(L5="Voicemail",L5="No answer"),"High",IF(L5="Answering service","Medium","Low"))) | N5: Paying | O5: 46291 | P5: Day-30 pilot review meeting | Q5: 46297 | R5: =IF(Q5="","",Q5-TODAY()) | S5: Founding Starter | T5: =IF(OR(S5="",N5<>"Paying"),"",IFERROR(INDEX(Plans!$B$2:$B$20,MATCH(S5,Plans!$A$2:$A$20,0)),"")) | U5: Fictional example row. Went to voicemail at 7:40 PM. Owner interested in estimate follow-ups. Delete this row when you start.
M6: =IF(L6="","",IF(OR(L6="Voicemail",L6="No answer"),"High",IF(L6="Answering service","Medium","Low"))) | R6: =IF(Q6="","",Q6-TODAY()) | T6: =IF(OR(S6="",N6<>"Paying"),"",IFERROR(INDEX(Plans!$B$2:$B$20,MATCH(S6,Plans!$A$2:$A$20,0)),""))
M7: =IF(L7="","",IF(OR(L7="Voicemail",L7="No answer"),"High",IF(L7="Answering service","Medium","Low"))) | R7: =IF(Q7="","",Q7-TODAY()) | T7: =IF(OR(S7="",N7<>"Paying"),"",IFERROR(INDEX(Plans!$B$2:$B$20,MATCH(S7,Plans!$A$2:$A$20,0)),""))
M8: =IF(L8="","",IF(OR(L8="Voicemail",L8="No answer"),"High",IF(L8="Answering service","Medium","Low"))) | R8: =IF(Q8="","",Q8-TODAY()) | T8: =IF(OR(S8="",N8<>"Paying"),"",IFERROR(INDEX(Plans!$B$2:$B$20,MATCH(S8,Plans!$A$2:$A$20,0)),""))
M9: =IF(L9="","",IF(OR(L9="Voicemail",L9="No answer"),"High",IF(L9="Answering service","Medium","Low"))) | R9: =IF(Q9="","",Q9-TODAY()) | T9: =IF(OR(S9="",N9<>"Paying"),"",IFERROR(INDEX(Plans!$B$2:$B$20,MATCH(S9,Plans!$A$2:$A$20,0)),""))
M10: =IF(L10="","",IF(OR(L10="Voicemail",L10="No answer"),"High",IF(L10="Answering service","Medium","Low"))) | R10: =IF(Q10="","",Q10-TODAY()) | T10: =IF(OR(S10="",N10<>"Paying"),"",IFERROR(INDEX(Plans!$B$2:$B$20,MATCH(S10,Plans!$A$2:$A$20,0)),""))
M11: =IF(L11="","",IF(OR(L11="Voicemail",L11="No answer"),"High",IF(L11="Answering service","Medium","Low"))) | R11: =IF(Q11="","",Q11-TODAY()) | T11: =IF(OR(S11="",N11<>"Paying"),"",IFERROR(INDEX(Plans!$B$2:$B$20,MATCH(S11,Plans!$A$2:$A$20,0)),""))
M12: =IF(L12="","",IF(OR(L12="Voicemail",L12="No answer"),"High",IF(L12="Answering service","Medium","Low"))) | R12: =IF(Q12="","",Q12-TODAY()) | T12: =IF(OR(S12="",N12<>"Paying"),"",IFERROR(INDEX(Plans!$B$2:$B$20,MATCH(S12,Plans!$A$2:$A$20,0)),""))
M13: =IF(L13="","",IF(OR(L13="Voicemail",L13="No answer"),"High",IF(L13="Answering service","Medium","Low"))) | R13: =IF(Q13="","",Q13-TODAY()) | T13: =IF(OR(S13="",N13<>"Paying"),"",IFERROR(INDEX(Plans!$B$2:$B$20,MATCH(S13,Plans!$A$2:$A$20,0)),""))
M14: =IF(L14="","",IF(OR(L14="Voicemail",L14="No answer"),"High",IF(L14="Answering service","Medium","Low"))) | R14: =IF(Q14="","",Q14-TODAY()) | T14: =IF(OR(S14="",N14<>"Paying"),"",IFERROR(INDEX(Plans!$B$2:$B$20,MATCH(S14,Plans!$A$2:$A$20,0)),""))
M15: =IF(L15="","",IF(OR(L15="Voicemail",L15="No answer"),"High",IF(L15="Answering service","Medium","Low"))) | R15: =IF(Q15="","",Q15-TODAY()) | T15: =IF(OR(S15="",N15<>"Paying"),"",IFERROR(INDEX(Plans!$B$2:$B$20,MATCH(S15,Plans!$A$2:$A$20,0)),""))
M16: =IF(L16="","",IF(OR(L16="Voicemail",L16="No answer"),"High",IF(L16="Answering service","Medium","Low"))) | R16: =IF(Q16="","",Q16-TODAY()) | T16: =IF(OR(S16="",N16<>"Paying"),"",IFERROR(INDEX(Plans!$B$2:$B$20,MATCH(S16,Plans!$A$2:$A$20,0)),""))
M17: =IF(L17="","",IF(OR(L17="Voicemail",L17="No answer"),"High",IF(L17="Answering service","Medium","Low"))) | R17: =IF(Q17="","",Q17-TODAY()) | T17: =IF(OR(S17="",N17<>"Paying"),"",IFERROR(INDEX(Plans!$B$2:$B$20,MATCH(S17,Plans!$A$2:$A$20,0)),""))
... M404: =IF(L404="","",IF(OR(L404="Voicemail",L404="No answer"),"High",IF(L404="Answering service","Medium","Low"))) | R404: =IF(Q404="","",Q404-TODAY()) | T404: =IF(OR(S404="",N404<>"Paying"),"",IFERROR(INDEX(Plans!$B$2:$B$20,MATCH(S404,Plans!$A$2:$A$20,0)),""))

Sheet Pipeline
B2: Pipeline summary
B3: Updates automatically from the Leads tab (the example row is included until you delete it).
B5: Stage | C5: Companies | D5: % of total
B6: New | C6: =COUNTIF(Leads!$N$5:$N$404,B6) | D6: =IF($C$16=0,0,C6/$C$16)
B7: Contacted | C7: =COUNTIF(Leads!$N$5:$N$404,B7) | D7: =IF($C$16=0,0,C7/$C$16)
B8: Replied | C8: =COUNTIF(Leads!$N$5:$N$404,B8) | D8: =IF($C$16=0,0,C8/$C$16)
B9: Meeting booked | C9: =COUNTIF(Leads!$N$5:$N$404,B9) | D9: =IF($C$16=0,0,C9/$C$16)
B10: Demo done | C10: =COUNTIF(Leads!$N$5:$N$404,B10) | D10: =IF($C$16=0,0,C10/$C$16)
B11: Pilot | C11: =COUNTIF(Leads!$N$5:$N$404,B11) | D11: =IF($C$16=0,0,C11/$C$16)
B12: Paying | C12: =COUNTIF(Leads!$N$5:$N$404,B12) | D12: =IF($C$16=0,0,C12/$C$16)
B13: Not now | C13: =COUNTIF(Leads!$N$5:$N$404,B13) | D13: =IF($C$16=0,0,C13/$C$16)
B14: Not interested | C14: =COUNTIF(Leads!$N$5:$N$404,B14) | D14: =IF($C$16=0,0,C14/$C$16)
B16: Total companies | C16: =SUM(C6:C14)
B18: Key numbers
B19: Monthly recurring revenue (MRR) | C19: =SUM(Leads!$T$5:$T$404)
B20: Paying customers | C20: =C12
B21: Pilots running | C21: =C11
B22: Contacted → replied or better | C22: =IF(SUM(C7:C14)=0,0,SUM(C8:C12)/SUM(C7:C14))
B23: Demo done → pilot or paying | C23: =IF(SUM(C10:C12)=0,0,SUM(C11:C12)/SUM(C10:C12))
B24: Follow-ups overdue | C24: =SUMPRODUCT((Leads!$Q$5:$Q$404<>"")*(Leads!$Q$5:$Q$404<TODAY())*(Leads!$N$5:$N$404<>"Paying")*(Leads!$N$5:$N$404<>"Not interested"))
B26: After-hours test results
B27: Companies tested | C27: =COUNTA(Leads!$L$5:$L$404)-COUNTIF(Leads!$L$5:$L$404,"Not tested")
B28: Went to voicemail / no answer | C28: =COUNTIF(Leads!$L$5:$L$404,"Voicemail")+COUNTIF(Leads!$L$5:$L$404,"No answer")
B29: % missed after hours | C29: =IF(C27=0,0,C28/C27) | D29: ← great line for emails: “X of Y local shops I called after 6 PM went to voicemail.”

Sheet Pilot results
A1: Pilot results (one row per pilot customer)
A2: Enter the counts from the CallFlow dashboard and the customer's real invoice amounts at day 30. Grey columns calculate.
A4: Company | B4: Pilot start | C4: Missed calls texted back | D4: Booked from text-back | E4: Avg repair ticket ($) | F4: After-hours calls booked | G4: Estimates followed up | H4: Estimates won after follow-up | I4: Value of estimates won ($) | J4: Revenue recovered ($) | K4: Plan price ($/mo) | L4: Return on price (x) | M4: Testimonial / case study OK?
A5: EXAMPLE — Wasatch Comfort (fictional) | B5: 46262 | C5: 23 | D5: 6 | E5: 480 | F5: 2 | G5: 9 | H5: 1 | I5: 7400 | J5: =IF(A5="","",(D5+F5)*E5+I5) | K5: 199 | L5: =IF(OR(J5="",K5="",K5=0),"",J5/K5) | M5: Yes
J6: =IF(A6="","",(D6+F6)*E6+I6) | L6: =IF(OR(J6="",K6="",K6=0),"",J6/K6)
J7: =IF(A7="","",(D7+F7)*E7+I7) | L7: =IF(OR(J7="",K7="",K7=0),"",J7/K7)
J8: =IF(A8="","",(D8+F8)*E8+I8) | L8: =IF(OR(J8="",K8="",K8=0),"",J8/K8)
J9: =IF(A9="","",(D9+F9)*E9+I9) | L9: =IF(OR(J9="",K9="",K9=0),"",J9/K9)
J10: =IF(A10="","",(D10+F10)*E10+I10) | L10: =IF(OR(J10="",K10="",K10=0),"",J10/K10)
J11: =IF(A11="","",(D11+F11)*E11+I11) | L11: =IF(OR(J11="",K11="",K11=0),"",J11/K11)
J12: =IF(A12="","",(D12+F12)*E12+I12) | L12: =IF(OR(J12="",K12="",K12=0),"",J12/K12)
J13: =IF(A13="","",(D13+F13)*E13+I13) | L13: =IF(OR(J13="",K13="",K13=0),"",J13/K13)
J14: =IF(A14="","",(D14+F14)*E14+I14) | L14: =IF(OR(J14="",K14="",K14=0),"",J14/K14)
J15: =IF(A15="","",(D15+F15)*E15+I15) | L15: =IF(OR(J15="",K15="",K15=0),"",J15/K15)
J16: =IF(A16="","",(D16+F16)*E16+I16) | L16: =IF(OR(J16="",K16="",K16=0),"",J16/K16)
J17: =IF(A17="","",(D17+F17)*E17+I17) | L17: =IF(OR(J17="",K17="",K17=0),"",J17/K17)
... J34: =IF(A34="","",(D34+F34)*E34+I34) | L34: =IF(OR(J34="",K34="",K34=0),"",J34/K34)
A37: Example row numbers are fictional and only show the format.

Sheet Plans
A1: Plan | B1: Monthly price ($) | C1: Note
A2: Starter | B2: 199 | C2: Price from the CallFlow app
A3: Growth | B3: 399 | C3: Price from the CallFlow app
A4: Pro | B4: 699 | C4: Price from the CallFlow app
A5: Founding Starter | B5: 99.5 | C5: Assumption: 50% off Starter for first 6 months (sales/05-pricing-and-pilot.md). Edit if you choose a different offer.
A6: Founding Growth | B6: 199.5 | C6: Assumption: 50% off Growth for first 6 months. Edit if you choose a different offer.
